arg_needle/__init__.py
arg_needle/arg_needle_hashing_pybind.cpython-39-x86_64-linux-gnu.so
arg_needle/decoders.py
arg_needle/inference.py
arg_needle/simulator.py
arg_needle/utils.py
arg_needle/resources/30-100-2000_CEU.decodingQuantities.gz
arg_needle/resources/CEU.demo
arg_needle/resources/ukb_chr2_spectrum.tsv
arg_needle/scripts/README.md
arg_needle/scripts/__init__.py
arg_needle/scripts/infer_args.py
arg_needle/scripts/infer_args_advanced.py
arg_needle/scripts/prepare_example.py
arg_needle.libs/libboost_iostreams-5e889418.so.1.66.0
arg_needle.libs/libboost_regex-2b30dfd4.so.1.66.0
arg_needle.libs/libbz2-a1e77c99.so.1.0.6
arg_needle.libs/libicudata-05640f77.so.60.3
arg_needle.libs/libicui18n-4fcc01ea.so.60.3
arg_needle.libs/libicuuc-14201aad.so.60.3
arg_needle.libs/liblzma-51a76f52.so.5.2.4
arg_needle-1.1.0.dist-info/METADATA
arg_needle-1.1.0.dist-info/WHEEL
arg_needle-1.1.0.dist-info/entry_points.txt
arg_needle-1.1.0.dist-info/RECORD
arg_needle-1.1.0.dist-info/licenses/LICENSE
