Metadata-Version: 2.2
Name: arg-needle
Version: 1.1.0
Summary: Ancestral recombination graph (ARG)
Author: ARG-Needle Developers
Classifier: Development Status :: 4 - Beta
Classifier: License :: OSI Approved :: GNU General Public License v3 or later (GPLv3+)
Classifier: Programming Language :: Python :: 3 :: Only
Classifier: Programming Language :: Python :: 3.9
Classifier: Programming Language :: Python :: 3.10
Classifier: Programming Language :: Python :: 3.11
Classifier: Programming Language :: Python :: 3.12
Classifier: Programming Language :: Python :: 3.13
Classifier: Programming Language :: Python :: 3.14
Requires-Python: >=3.9
Requires-Dist: arg-needle-lib>=1.2.0
Requires-Dist: asmc-asmc>=1.4.0
Requires-Dist: fastcluster
Requires-Dist: msprime>=1.3.0
Requires-Dist: numpy>=1.17.0
Requires-Dist: pandas
Requires-Dist: psutil
Requires-Dist: tskit>=1.0.0
Provides-Extra: dev
Requires-Dist: pytest; extra == "dev"
Requires-Dist: h5py; extra == "dev"
